    {
        "statusCode": 200,
        "data": {
            "users": [
                {
                    "id": 27087,
                    "first_name": "GEORGE ALEXANDRE SANTINO",
                    "last_name": null,
                    "number_id": "13810978809",
                    "email": "george.santino@grupoccr.com.br",
                    "active": true,
                    "created": "2020-01-31T20:17:51-02:00",
                    "company": {
                        "id": 2477,
                        "name": "39-METRO BAHIA"
                    },
                    "department": {
                        "id": 3397,
                        "name": "GESTAO DO ATENDIMENTO E INTERACAO COM O CLIENTE"
                    },
                    "forms": [
                        {
                            "id": 254,
                            "users_id": 27087,
                            "forms_id": 70,
                            "forms_users_id": 24232,
                            "created": "2020-02-27T17:38:12-03:00",
                            "approved_date": "2020-02-27T17:38:12-03:00",
                            "status": {
                                "id": 14,
                                "title": "Pendente"
                            },
                            "manager": null,
                            "author": {
                                "id": 27087,
                                "first_name": "GEORGE ALEXANDRE SANTINO",
                                "last_name": null,
                                "number_id": "13810978809",
                                "email": "george.santino@grupoccr.com.br",
                                "active": true
                            },
                            "questions": {
                                "0": {
                                    "id": 1549,
                                    "parent": null,
                                    "title": "Você está preenchendo para outro colaborador? ",
                                    "value": "Não"
                                },
                                "2": {
                                    "id": 1401,
                                    "parent": null,
                                    "title": "Algum outro colaborador/Administrador da CCR estava presente?",
                                    "value": "Sim"
                                },
                                "3": {
                                    "id": 1402,
                                    "parent": null,
                                    "title": "Adicionar Colaborador/Administrador:",
                                    "value": [
                                        [
                                            {
                                                "id": 1403,
                                                "parent": 1402,
                                                "title": "Nome:",
                                                "value": "Leonardo Henrique Balbino"
                                            },
                                            {
                                                "id": 1404,
                                                "parent": 1402,
                                                "title": "Cargo:",
                                                "value": "Gestor do Atendimento"
                                            },
                                            {
                                                "id": 1405,
                                                "parent": 1402,
                                                "title": "Divisão:",
                                                "value": "Mobilidade"
                                            },
                                            {
                                                "id": 1406,
                                                "parent": 1402,
                                                "title": "Unidade de Negócios:",
                                                "value": "CCR Metrô Bahia"
                                            }
                                        ]
                                    ]
                                },
                                "5": {
                                    "id": 1396,
                                    "parent": null,
                                    "title": "Dados dos Colaboradores/Administradores presentes na interação",
                                    "value": [
                                        [
                                            {
                                                "id": 1397,
                                                "parent": 1396,
                                                "title": "Nome completo:",
                                                "value": "GEORGE ALEXANDRE SANTINO"
                                            },
                                            {
                                                "id": 1398,
                                                "parent": 1396,
                                                "title": "Cargo:",
                                                "value": "Coordenador do CCO"
                                            },
                                            {
                                                "id": 1399,
                                                "parent": 1396,
                                                "title": "Divisão:",
                                                "value": "Mobilidade"
                                            },
                                            {
                                                "id": 1400,
                                                "parent": 1396,
                                                "title": "Unidade de Negócios:",
                                                "value": "CCR Metrô Bahia"
                                            }
                                        ]
                                    ]
                                },
                                "6": {
                                    "id": 1408,
                                    "parent": null,
                                    "title": "Dados dos Agentes Públicos presentes na interação",
                                    "value": [
                                        [
                                            {
                                                "id": 1409,
                                                "parent": 1408,
                                                "title": "Nome do Agente Público:",
                                                "value": "Hernani Baltazar"
                                            },
                                            {
                                                "id": 1410,
                                                "parent": 1408,
                                                "title": "Órgão:",
                                                "value": "CTB"
                                            },
                                            {
                                                "id": 1411,
                                                "parent": 1408,
                                                "title": "Área de atuação do Agente Público:",
                                                "value": "Diretoria de obras"
                                            }
                                        ],
                                        [
                                            {
                                                "id": 1409,
                                                "parent": 1408,
                                                "title": "Nome do Agente Público:",
                                                "value": "Aldo Pinto"
                                            },
                                            {
                                                "id": 1410,
                                                "parent": 1408,
                                                "title": "Órgão:",
                                                "value": "Diretoria de obras"
                                            },
                                            {
                                                "id": 1411,
                                                "parent": 1408,
                                                "title": "Área de atuação do Agente Público:",
                                                "value": "Diretoria de obras"
                                            }
                                        ],
                                        [
                                            {
                                                "id": 1409,
                                                "parent": 1408,
                                                "title": "Nome do Agente Público:",
                                                "value": "Geraldo Teixeira"
                                            },
                                            {
                                                "id": 1410,
                                                "parent": 1408,
                                                "title": "Órgão:",
                                                "value": "GMB fiscalizadora"
                                            },
                                            {
                                                "id": 1411,
                                                "parent": 1408,
                                                "title": "Área de atuação do Agente Público:",
                                                "value": "fiscalizadora do metro Bahia"
                                            }
                                        ]
                                    ]
                                },
                                "7": {
                                    "id": 1412,
                                    "parent": null,
                                    "title": "Data da interação:",
                                    "value": "16/01/2020"
                                },
                                "8": {
                                    "id": 1413,
                                    "parent": null,
                                    "title": "Local da interação:",
                                    "value": "sala de reuniões da CTB no canteiro de Retiro"
                                },
                                "9": {
                                    "id": 1414,
                                    "parent": null,
                                    "title": "Horário de Início:",
                                    "value": "09:30"
                                },
                                "10": {
                                    "id": 1415,
                                    "parent": null,
                                    "title": "Horário de Término:",
                                    "value": "11:30"
                                },
                                "11": {
                                    "id": 1416,
                                    "parent": null,
                                    "title": "Quem motivou a interação?",
                                    "value": "Agente Público"
                                },
                                "13": {
                                    "id": 1417,
                                    "parent": null,
                                    "title": "Assunto discutido:",
                                    "value": "Outros"
                                },
                                "14": {
                                    "id": 2301,
                                    "parent": null,
                                    "title": "Justifique:",
                                    "value": null
                                },
                                "15": {
                                    "id": 1418,
                                    "parent": null,
                                    "title": "Qual?",
                                    "value": "auxilio técnico para calculo da quantidade de trens e modelo de circulação para o modal VLT, recém concedido pelo Governo do Estado.\r\nAvaliamos juntos o melhor modelo de circulação frente ao provável fluxo de clientes no futuro trecho do VLT"
                                },
                                "18": {
                                    "id": 1421,
                                    "parent": null,
                                    "title": "Houve formalização da interação em ata ou trocas de ofícios?",
                                    "value": "Não"
                                },
                                "20": {
                                    "id": 1423,
                                    "parent": null,
                                    "title": "A interação incluiu o custeio de algum tipo de hospitalidade (refeição, deslocamento, etc?)",
                                    "value": "Não"
                                },
                                "23": {
                                    "id": 1426,
                                    "parent": null,
                                    "title": "Houve algum pedido, sinalização, indicação, requerimento ou conduta imprópria por qualquer dos presentes?",
                                    "value": "Não"
                                },
                                "26": {
                                    "id": 1429,
                                    "parent": null,
                                    "title": "Houve algum pedido, sinalização, indicação ou requerimento para doação ou patrocínio de algum projeto ou evento?",
                                    "value": "Não"
                                },
                                "28": {
                                    "id": 1431,
                                    "parent": null,
                                    "title": "Anexe aqui ( Opcional):",
                                    "value": null
                                },
                                "29": {
                                    "id": 1432,
                                    "parent": null,
                                    "title": "Deseja informar algo não listado neste formulário?",
                                    "value": "Não"
                                },
                                "32": {
                                    "id": 1435,
                                    "parent": null,
                                    "title": "Declaro que as informações acima são verídicas completas e corretas, me responsabilizando pelo conteúdo nela contido",
                                    "value": null
                                }
                            }
                        }
                    ]
                }
            ]
        }
    }